aspecd/__init__.py
aspecd/analysis.py
aspecd/annotation.py
aspecd/dataset.py
aspecd/exceptions.py
aspecd/history.py
aspecd/infofile.py
aspecd/io.py
aspecd/metadata.py
aspecd/model.py
aspecd/plotting.py
aspecd/processing.py
aspecd/recipe_mapper.yaml
aspecd/report.py
aspecd/system.py
aspecd/table.py
aspecd/tasks.py
aspecd/utils.py
aspecd/templates/report/latex/de/abbildung.tex
aspecd/templates/report/latex/de/analyseschritt.tex
aspecd/templates/report/latex/de/anmerkung_kommentar.tex
aspecd/templates/report/latex/de/basis.tex
aspecd/templates/report/latex/de/datensatz.tex
aspecd/templates/report/latex/de/kolophon.tex
aspecd/templates/report/latex/de/metadaten_experimentell.tex
aspecd/templates/report/latex/de/metadaten_gerechnet.tex
aspecd/templates/report/latex/de/verarbeitungsschritt.tex
aspecd/templates/report/latex/en/analysis_step.tex
aspecd/templates/report/latex/en/annotation_comment.tex
aspecd/templates/report/latex/en/base.tex
aspecd/templates/report/latex/en/colophon.tex
aspecd/templates/report/latex/en/dataset.tex
aspecd/templates/report/latex/en/figure.tex
aspecd/templates/report/latex/en/metadata_calculated.tex
aspecd/templates/report/latex/en/metadata_experimental.tex
aspecd/templates/report/latex/en/processing_step.tex
aspecd/templates/report/txt/en/analysis_step.txt
aspecd/templates/report/txt/en/annotation_comment.txt
aspecd/templates/report/txt/en/colophon.txt
aspecd/templates/report/txt/en/dataset.txt
aspecd/templates/report/txt/en/figure.txt
aspecd/templates/report/txt/en/metadata_calculated.txt
aspecd/templates/report/txt/en/metadata_experimental.txt
aspecd/templates/report/txt/en/processing_step.txt
aspecd-0.12.0.dist-info/LICENSE
aspecd-0.12.0.dist-info/METADATA
aspecd-0.12.0.dist-info/WHEEL
aspecd-0.12.0.dist-info/entry_points.txt
aspecd-0.12.0.dist-info/top_level.txt
aspecd-0.12.0.dist-info/RECORD
