Metadata-Version: 2.1
Name: aspecd
Version: 0.12.0
Summary: Framework for handling spectroscopic data.
Home-page: https://www.aspecd.de/
Author: Till Biskup
Author-email: till@till-biskup.de
License: BSD
Project-URL: Documentation, https://docs.aspecd.de/
Project-URL: Source, https://github.com/tillbiskup/aspecd
Keywords: spectroscopy,data processing and analysis,reproducible science,reproducible research,good scientific practice,recipe-driven data analysis
Classifier: Programming Language :: Python :: 3
Classifier: Programming Language :: Python :: 3.7
Classifier: Programming Language :: Python :: 3.8
Classifier: Programming Language :: Python :: 3.9
Classifier: License :: OSI Approved :: BSD License
Classifier: Operating System :: OS Independent
Classifier: Intended Audience :: Science/Research
Classifier: Development Status :: 5 - Production/Stable
Classifier: Topic :: Scientific/Engineering
Classifier: Topic :: Scientific/Engineering :: Chemistry
Classifier: Topic :: Scientific/Engineering :: Physics
Classifier: Topic :: Software Development :: Libraries :: Application Frameworks
Requires-Python: >=3.7
License-File: LICENSE
Requires-Dist: jinja2>=3.0
Requires-Dist: matplotlib
Requires-Dist: numpy
Requires-Dist: scipy>=0.14
Requires-Dist: oyaml
Requires-Dist: asdf
Requires-Dist: bibrecord>=0.2
Requires-Dist: setuptools
Provides-Extra: dev
Requires-Dist: prospector; extra == "dev"
Requires-Dist: pyroma; extra == "dev"
Requires-Dist: bandit; extra == "dev"
Requires-Dist: black; extra == "dev"
Provides-Extra: docs
Requires-Dist: sphinx; extra == "docs"
Requires-Dist: sphinx-rtd-theme; extra == "docs"
Requires-Dist: sphinx-multiversion; extra == "docs"
Provides-Extra: deployment
Requires-Dist: build; extra == "deployment"
Requires-Dist: twine; extra == "deployment"
